imWEBs/__init__.py
imWEBs/folder_base.py
imWEBs/imwebs.py
imWEBs/inputs.py
imWEBs/iuh.py
imWEBs/lookup.py
imWEBs/names.py
imWEBs/outputs.py
imWEBs/parameters.py
imWEBs/raster_extension.py
imWEBs/vector_extension.py
imWEBs/bmp/bmp.py
imWEBs/bmp/bmp_areal.py
imWEBs/bmp/bmp_areal_manure_feedlot.py
imWEBs/bmp/bmp_areal_manure_storage.py
imWEBs/bmp/bmp_manure_adjustment.py
imWEBs/bmp/bmp_offsite_wintering.py
imWEBs/bmp/bmp_reach.py
imWEBs/bmp/bmp_reach_grass_waterway.py
imWEBs/bmp/bmp_reach_manure_catch_basin.py
imWEBs/bmp/bmp_reach_point_source.py
imWEBs/bmp/bmp_reach_reservoir.py
imWEBs/bmp/bmp_reach_wetland.py
imWEBs/bmp/bmp_structure.py
imWEBs/bmp/bmp_structure_dugout.py
imWEBs/bmp/bmp_structure_riparian_buffer.py
imWEBs/bmp/bmp_structure_tile_drain.py
imWEBs/bmp/bmp_structure_wascob.py
imWEBs/bmp/bmp_type.py
imWEBs/bmp/crop_rotation/crop-lookup-after-2010.csv
imWEBs/bmp/crop_rotation/crop-lookup-before-2010.csv
imWEBs/bmp/crop_rotation/crop-management.csv
imWEBs/bmp/crop_rotation/crop_rotation.py
imWEBs/bmp/crop_rotation/default_crop_management.csv
imWEBs/bmp/crop_rotation/default_fertilizer_management.csv
imWEBs/bmp/crop_rotation/default_tillage_management.csv
imWEBs/bmp/crop_rotation/fertilizer-management.csv
imWEBs/bmp/crop_rotation/grazing-management.csv
imWEBs/bmp/crop_rotation/single_crop.py
imWEBs/bmp/crop_rotation/tillage-management.csv
imWEBs/config/config.py
imWEBs/config/model_config.py
imWEBs/config/scenario_config.py
imWEBs/database/__init__.py
imWEBs/database/database_base.py
imWEBs/database/bmp/__init__.py
imWEBs/database/bmp/bmp_01_point_source.py
imWEBs/database/bmp/bmp_02_flow_diversion.py
imWEBs/database/bmp/bmp_03_reservoir.py
imWEBs/database/bmp/bmp_04_riparian_wetland.py
imWEBs/database/bmp/bmp_05_riparian_buffer.py
imWEBs/database/bmp/bmp_06_grass_waterway.py
imWEBs/database/bmp/bmp_07_vegetation_filter_strip.py
imWEBs/database/bmp/bmp_08_pond.py
imWEBs/database/bmp/bmp_09_isolated_wetland.py
imWEBs/database/bmp/bmp_10_terrace.py
imwebs-0.0.37.dist-info/METADATA
imwebs-0.0.37.dist-info/WHEEL
imwebs-0.0.37.dist-info/licenses/LICENSE
imwebs-0.0.37.dist-info/RECORD
