Metadata-Version: 2.4
Name: imWEBs
Version: 0.0.37
Summary: A package to create imWEBs models
Author: University of Guelph
License-File: LICENSE
Classifier: License :: OSI Approved :: MIT License
Classifier: Programming Language :: Python
Requires-Python: >=3.9
Requires-Dist: geopandas
Requires-Dist: numpy
Requires-Dist: pandas
Requires-Dist: sqlalchemy
Requires-Dist: whitebox-workflows==1.3.2
